hun0219_cmd/__init__.py
hun0219_cmd/cmd.py
hun0219_cmd-0.2.0.dist-info/METADATA
hun0219_cmd-0.2.0.dist-info/WHEEL
hun0219_cmd-0.2.0.dist-info/entry_points.txt
hun0219_cmd-0.2.0.dist-info/top_level.txt
hun0219_cmd-0.2.0.dist-info/RECORD
