Metadata-Version: 2.1
Name: hun0219_cmd
Version: 0.2.0
Summary: Default template for PDM package
Author-email: hun0219 <gsw98000@gmail.com>
License: MIT
Requires-Python: >=3.9
Requires-Dist: hun0219-lotto >=0.1.2
